[
    {
        "kind": "protocol/member",
        "name": "fuchsia.diagnostics.host/ArchiveAccessor.StreamDiagnostics",
        "strictness": "flexible",
        "ordinal": "2982317777147939163",
        "direction": "two_way",
        "request": "fuchsia.diagnostics.host/ArchiveAccessorStreamDiagnosticsRequest",
        "response": "fuchsia.diagnostics.host/ArchiveAccessor_StreamDiagnostics_Response"
    },
    {
        "kind": "protocol",
        "name": "fuchsia.diagnostics.host/ArchiveAccessor",
        "openness": "open",
        "transport": "channel"
    },
    {
        "kind": "struct/member",
        "name": "fuchsia.diagnostics.host/ArchiveAccessorStreamDiagnosticsRequest.parameters",
        "ordinal": "1",
        "type": "fuchsia.diagnostics/StreamParameters"
    },
    {
        "kind": "struct/member",
        "name": "fuchsia.diagnostics.host/ArchiveAccessorStreamDiagnosticsRequest.stream",
        "ordinal": "2",
        "type": "zx/Handle:<SOCKET,zx.WRITE,zx.WAIT>"
    },
    {
        "kind": "struct",
        "name": "fuchsia.diagnostics.host/ArchiveAccessorStreamDiagnosticsRequest",
        "resourceness": "resource"
    },
    {
        "kind": "library",
        "name": "fuchsia.diagnostics.host"
    }
]
